xepmts_endpoints/__init__.py
xepmts_endpoints/cli.py
xepmts_endpoints/config.py
xepmts_endpoints/endpoint_templates/accounts.yml
xepmts_endpoints/endpoint_templates/afterpulse_spectra.yml
xepmts_endpoints/endpoint_templates/afterpulses.yml
xepmts_endpoints/endpoint_templates/current_changes.yml
xepmts_endpoints/endpoint_templates/dark_count_rates.yml
xepmts_endpoints/endpoint_templates/gain_measurements.yml
xepmts_endpoints/endpoint_templates/gain_models.yml
xepmts_endpoints/endpoint_templates/gains.yml
xepmts_endpoints/endpoint_templates/hv_events.yml
xepmts_endpoints/endpoint_templates/installs.yml
xepmts_endpoints/endpoint_templates/pmt_errors.yml
xepmts_endpoints/endpoint_templates/pmts.yml
xepmts_endpoints/endpoint_templates/spe_acceptance.yml
xepmts_endpoints/endpoint_templates/tester.py
xepmts_endpoints/endpoint_templates/voltage_changes.yml
xepmts_endpoints/endpoint_templates/voltage_maps.yml
xepmts_endpoints/endpoints.py
xepmts_endpoints/utils.py
xepmts_endpoints-0.1.4.dist-info/entry_points.txt
xepmts_endpoints-0.1.4.dist-info/LICENSE
xepmts_endpoints-0.1.4.dist-info/WHEEL
xepmts_endpoints-0.1.4.dist-info/METADATA
xepmts_endpoints-0.1.4.dist-info/RECORD
