Metadata-Version: 2.1
Name: xepmts-endpoints
Version: 0.1.4
Summary: Top-level package for xepmts-endpoints.
Home-page: https://github.com/jmosbacher/xepmts_endpoints
License: MIT
Author: Yossi Mosbacher
Author-email: joe.mosbacher@gmail.com
Requires-Python: >=3.7
Classifier: Development Status :: 2 - Pre-Alpha
Classifier: Intended Audience :: Developers
Classifier: License :: OSI Approved :: MIT License
Classifier: Natural Language :: English
Classifier: Programming Language :: Python :: 3
Classifier: Programming Language :: Python :: 3.7
Classifier: Programming Language :: Python :: 3.8
Requires-Dist: PyYAML (>=5.4.1,<6.0.0)
Requires-Dist: click
